wmr_cba/__init__.py
wmr_cba/_test_cba4.py
wmr_cba/_test_package.py
wmr_cba/wmr_cba.py
wmr_cba-1.1.0.dist-info/LICENSE
wmr_cba-1.1.0.dist-info/METADATA
wmr_cba-1.1.0.dist-info/WHEEL
wmr_cba-1.1.0.dist-info/top_level.txt
wmr_cba-1.1.0.dist-info/RECORD
