Metadata-Version: 2.1
Name: wmr-cba
Version: 1.1.0
Summary: Python module for controlling West Mountain Radio CBA devices.
Home-page: https://github.com/da66en/python_wmr_cba
Author: Darren Rook (da66en)
Author-email: route66@gmail.com
License: UNKNOWN
Platform: UNKNOWN
Classifier: Programming Language :: Python :: 3
Classifier: License :: OSI Approved :: MIT License
Classifier: Operating System :: OS Independent
